flask_bowercdn
