Metadata-Version: 1.1
Name: Flask-BowerCDN
Version: 0.3.0
Summary: Work easily with Bower and CDN content.
Home-page: https://bitbucket.org/romabysen/flask-bowercdn
Author: Lars Hansson
Author-email: romabysen@gmail.com
License: BSD
Platform: any
Classifier: Environment :: Web Environment
Classifier: Intended Audience :: Developers
Classifier: License :: OSI Approved :: BSD License
Classifier: Operating System :: OS Independent
Classifier: Programming Language :: Python
Classifier: Topic :: Internet :: WWW/HTTP :: Dynamic Content
Classifier: Topic :: Software Development :: Libraries :: Python Modules
